{"address": "1234 NW 23rd Avenue, Portland, OR 97210", "restaurant_density": {"total_count_within_1km": 89, "nearest_100m_count": 6, "cuisine_diversity_count": 11, "rating": "Exceptional - One of Portland's highest restaurant densities"}, "cuisine_categories": {"asian": {"count": 28, "display_order": 1}, "european": {"count": 18, "display_order": 2}, "latin_american": {"count": 14, "display_order": 3}, "american": {"count": 15, "display_order": 4}, "middle_eastern": {"count": 8, "display_order": 5}, "coffee_cafes": {"count": 12, "display_order": 6}}, "nearest_full_list": [{"rank": 1, "name": "Tara Thai Northwest", "distance_m": 42, "cuisine": "Thai/Lao", "address": "1310 NW 23rd Ave", "features": ["takeout", "dine-in", "gluten-free options", "vegetarian options"]}, {"rank": 2, "name": "Top Burmese Burma Joy", "distance_m": 47, "cuisine": "Burmese/Asian", "address": "1305 NW 23rd Ave", "features": ["dine-in", "takeout", "vegan options", "family friendly"], "hours": "Mo-Su 11:30AM-9PM"}, {"rank": 3, "name": "Siri Indian Cuisine", "distance_m": 69, "cuisine": "Indian", "address": "1323 NW 23rd Ave", "features": ["dine-in", "takeout", "lunch buffet", "vegetarian"]}, {"rank": 4, "name": "Henry Higgins Boiled Bagels", "distance_m": 95, "cuisine": "Bagel/American", "address": "628 NW 23rd Ave", "features": ["dine-in", "takeout", "vegan bagels", "lunch", "cat cafe next door"], "hours": "Mo-Th 7AM-4PM; Fr 7AM-5PM; Sa 8AM-4PM; Su 8AM-3PM"}, {"rank": 5, "name": "Pepino's", "distance_m": 98, "cuisine": "Mexican", "address": "914 NW 23rd Ave", "features": ["dine-in", "takeout", "street tacos", "margaritas", "outdoor seating"], "hours": "Mo-Th 11AM-Midnight; Fr-Sa 11AM-1AM; Su 11AM-11PM"}, {"rank": 6, "name": "Case Study Coffee Roasters", "distance_m": 114, "cuisine": "Coffee Shop", "address": "1400 NW 23rd Ave", "features": ["dine-in", "wifi", "outdoor seating", "specialty coffee", "light lunch"], "hours": "7AM-4PM daily"}, {"rank": 7, "name": "Palomar", "distance_m": 143, "cuisine": "Latin/British Pub", "address": "1422 NW 23rd Ave", "features": ["dine-in", "cocktails", "rooftop patio", "live music"], "hours": "Mo-Th 5PM-Midnight; Fr-Sa 5PM-1AM; Su 5PM-11PM"}, {"rank": 8, "name": "Dorio Greek Taverna", "distance_m": 159, "cuisine": "Greek", "address": "1037 NW 23rd Ave", "features": ["dine-in", "takeout", "family style", "full bar", "wangus (Greek fries)"], "hours": "Mo-Th 4PM-10PM; Fr-Sa 4PM-11PM; Su 4PM-9PM"}, {"rank": 9, "name": "Matador", "distance_m": 163, "cuisine": "Mexican", "address": "1438 NW 23rd Ave", "features": ["dine-in", "cocktails", "street-style tacos", "happy hour"], "hours": "Mo-Th 4PM-Midnight; Fr-Sa 4PM-1AM; Su 4PM-Midnight"}, {"rank": 10, "name": "Grassa", "distance_m": 188, "cuisine": "Italian", "address": "1506 NW 23rd Ave", "features": ["dine-in", "pasta", "wine bar", "casual upscale"], "hours": "Mo-Th 5PM-10PM; Fr-Sa 5PM-11PM; Su 5PM-9PM"}], "themed_highlights": {"vegan_aware": ["Top Burmese Burma Joy", "Henry Higgins Boiled Bagels", "Memento Mori Cafe", "Mocado"], "dog_friendly_patios": "Yes - NW 23rd Ave patios widely allow dogs (Portland dog culture)", "outdoor_seating_count": 8, "wifi_venues_count": 6, "late_night_options": ["Pepino's (midnight)', 'Matador (midnight)', 'Palomar (1AM Fri/Sat)"], "brunch_spots_count": 5, "dinner_enthusiast_count": 12}, "data_metadata": {"source": "OpenStreetMap + cross-referenced city data", "analysis_method": "OSM amenity=restaurant/cafe/food queries within 1km radius; distance via OSRM", "collection_date": "2026-07-18", "radius_m": 1000, "license": "Open Database License (ODbL) 1.0"}}